github_binary_upload.py
github_binary_upload-0.1.10.dist-info/LICENSE
github_binary_upload-0.1.10.dist-info/METADATA
github_binary_upload-0.1.10.dist-info/WHEEL
github_binary_upload-0.1.10.dist-info/entry_points.txt
github_binary_upload-0.1.10.dist-info/top_level.txt
github_binary_upload-0.1.10.dist-info/RECORD
