Metadata-Version: 2.1
Name: github-binary-upload
Version: 0.1.10
Summary: github-binary-upload is a utility for publishing releases from tags with attached files on GitHub.
Home-page: https://github.com/sciapp/github-binary-upload
Author: Ingo Meyer
Author-email: i.meyer@fz-juelich.de
License: MIT
Keywords: git,GitHub,release,assets
Classifier: Development Status :: 5 - Production/Stable
Classifier: Environment :: Console
Classifier: Intended Audience :: Developers
Classifier: License :: OSI Approved :: MIT License
Classifier: Operating System :: MacOS
Classifier: Operating System :: POSIX :: Linux
Classifier: Programming Language :: Python
Classifier: Programming Language :: Python :: 3
Classifier: Programming Language :: Python :: 3.3
Classifier: Programming Language :: Python :: 3.4
Classifier: Programming Language :: Python :: 3.5
Classifier: Programming Language :: Python :: 3.6
Classifier: Programming Language :: Python :: 3.7
Classifier: Programming Language :: Python :: 3 :: Only
Classifier: Topic :: Software Development :: Version Control :: Git
Classifier: Topic :: Utilities
Requires-Python: ~=3.5
License-File: LICENSE
Requires-Dist: requests
Requires-Dist: yacl
